LICENSE.txt
MANIFEST.in
README.md
requirements-dev.txt
requirements.txt
setup.cfg
setup.py
fsnav/__init__.py
fsnav/core.py
fsnav/fg_tools.py
fsnav/settings.py
fsnav.egg-info/PKG-INFO
fsnav.egg-info/SOURCES.txt
fsnav.egg-info/dependency_links.txt
fsnav.egg-info/entry_points.txt
fsnav.egg-info/requires.txt
fsnav.egg-info/top_level.txt
fsnav.egg-info/zip-safe
fsnav/cmdl/__init__.py
fsnav/cmdl/count.py
fsnav/cmdl/nav.py
fsnav/cmdl/options.py
tests/__init__.py
tests/test_core.py
tests/test_fg_tools.py
tests/test_settings.py
tests/test_cmdl/__init__.py
tests/test_cmdl/test_count.py
tests/test_cmdl/test_nav.py
tests/test_cmdl/test_options.py