Metadata-Version: 1.1
Name: fsnav
Version: 0.9.2
Summary: FS Nav - File System Navigation shortcuts for the commandline
Home-page: https://github.com/geowurster/FS-Nav
Author: Kevin Wurster
Author-email: wursterk@gmail.com
License: New BSD License
